pathlib_mate/__init__.py
pathlib_mate/_paths.py
pathlib_mate/_version.py
pathlib_mate/api.py
pathlib_mate/hashes.py
pathlib_mate/helper.py
pathlib_mate/mate_attr_accessor.py
pathlib_mate/mate_hashes_methods.py
pathlib_mate/mate_mutate_methods.py
pathlib_mate/mate_path_filters.py
pathlib_mate/mate_tool_box.py
pathlib_mate/mate_tool_box_zip.py
pathlib_mate/pathlib2.py
pathlib_mate/str_encode.py
pathlib_mate/docs/__init__.py
pathlib_mate/tests/__init__.py
pathlib_mate/tests/helper.py
pathlib_mate/vendor/__init__.py
pathlib_mate/vendor/fileutils.py
pathlib_mate/vendor/pytest_cov_helper.py
pathlib_mate/vendor/six.py
pathlib_mate-1.3.2.dist-info/AUTHORS.rst
pathlib_mate-1.3.2.dist-info/LICENSE.txt
pathlib_mate-1.3.2.dist-info/METADATA
pathlib_mate-1.3.2.dist-info/WHEEL
pathlib_mate-1.3.2.dist-info/top_level.txt
pathlib_mate-1.3.2.dist-info/RECORD
